setup.py
mechloader/__init__.py
mechloader/dict_update.py
mechloader/test.py
mechloader.egg-info/PKG-INFO
mechloader.egg-info/SOURCES.txt
mechloader.egg-info/dependency_links.txt
mechloader.egg-info/requires.txt
mechloader.egg-info/top_level.txt