Metadata-Version: 1.1
Name: mechloader
Version: 0.0.2
Summary: Downloader for web based on mechanize
Home-page: https://github.com/viatoriche/mechloader
Author: viatoriche
Author-email: maxim@via-net.org
License: MIT
Download-URL: https://github.com/viatoriche/mechloader/tarball/0.0.2
Platform: UNKNOWN
